RobotFrameworkResultsToSlackChannel/__init__.py
RobotFrameworkResultsToSlackChannel/main.py
robotframework_results_to_slack_channel-1.0.1.dist-info/LICENSE
robotframework_results_to_slack_channel-1.0.1.dist-info/METADATA
robotframework_results_to_slack_channel-1.0.1.dist-info/WHEEL
robotframework_results_to_slack_channel-1.0.1.dist-info/top_level.txt
robotframework_results_to_slack_channel-1.0.1.dist-info/RECORD
